minjob/__init__.py
minjob/jobs.py
minjob/logger.py
minjob-0.1.0.dist-info/LICENSE
minjob-0.1.0.dist-info/METADATA
minjob-0.1.0.dist-info/WHEEL
minjob-0.1.0.dist-info/top_level.txt
minjob-0.1.0.dist-info/RECORD
