Metadata-Version: 2.1
Name: minjob
Version: 0.1.0
Summary: Minimal job monitor for multi-threaded Python applications
Home-page: https://github.com/madagra/minjob
Author: Mario Dagrada
Author-email: mariodagrada24@gmail.com
License: MIT
Platform: UNKNOWN
Requires-Python: >=3.7
